aware_test_runner/__init__.py
aware_test_runner/__main__.py
aware_test_runner/cli.py
aware_test_runner/test_runner.py
aware_test_runner/config/__init__.py
aware_test_runner/core/__init__.py
aware_test_runner/core/collector.py
aware_test_runner/core/discovery.py
aware_test_runner/core/executor.py
aware_test_runner/core/models.py
aware_test_runner/core/reporter.py
aware_test_runner/core/runtime/__init__.py
aware_test_runner/core/runtime/base.py
aware_test_runner/core/runtime/flutter.py
aware_test_runner/core/runtime/python.py
aware_test_runner/core/runtime/registry.py
aware_test_runner/data/__init__.py
aware_test_runner/utils/__init__.py
aware_test_runner/utils/helpers.py
aware_test_runner-0.2.0.dist-info/METADATA
aware_test_runner-0.2.0.dist-info/WHEEL
aware_test_runner-0.2.0.dist-info/entry_points.txt
aware_test_runner-0.2.0.dist-info/licenses/LICENSE
aware_test_runner-0.2.0.dist-info/RECORD
