Metadata-Version: 2.4
Name: aware-test-runner
Version: 0.2.0
Summary: Unified test runner for the Aware platform with OSS-ready packaging.
Project-URL: Homepage, https://pypi.org/project/aware-test-runner/
Project-URL: Documentation, https://github.com/aware-network/aware-sdk/tree/main/tools/test-runner/README.md
Project-URL: Changelog, https://github.com/aware-network/aware-sdk/tree/main/tools/test-runner/CHANGELOG.md
Project-URL: Source, https://github.com/aware-network/aware-sdk
Project-URL: Issues, https://github.com/aware-network/aware-sdk/issues
Author: Aware Team
License: MIT License
License-File: LICENSE
Keywords: automation,aware,ci,manifests,testing
Classifier: Development Status :: 3 - Alpha
Classifier: Intended Audience :: Developers
Classifier: License :: OSI Approved :: MIT License
Classifier: Operating System :: OS Independent
Classifier: Programming Language :: Python :: 3
Classifier: Programming Language :: Python :: 3 :: Only
Classifier: Programming Language :: Python :: 3.10
Classifier: Programming Language :: Python :: 3.11
Classifier: Programming Language :: Python :: 3.12
Classifier: Topic :: Software Development :: Testing
Requires-Python: >=3.10
Requires-Dist: pytest>=8.2
Provides-Extra: docs
Requires-Dist: mkdocs>=1.6; extra == 'docs'
Provides-Extra: internal
Provides-Extra: tests
Requires-Dist: pytest>=8.2; extra == 'tests'
